uarmserial/__init__.py
uarmserial/base.py
uarmserial/comm.py
uarmserial/transporter.py
uarmserial-0.0.26.dist-info/LICENSE
uarmserial-0.0.26.dist-info/METADATA
uarmserial-0.0.26.dist-info/WHEEL
uarmserial-0.0.26.dist-info/top_level.txt
uarmserial-0.0.26.dist-info/RECORD
