Metadata-Version: 2.1
Name: uarmserial
Version: 0.0.26
Summary: Python package for connecting to and communicating with a uARM Swift Pro robot
Home-page: https://github.com/ryankshah/uarmserial
Author: Ryan Shah
Author-email: ryan.k.shah@gmail.com
License: UNKNOWN
Platform: UNKNOWN
Classifier: Programming Language :: Python :: 3
Classifier: License :: OSI Approved :: MIT License
Classifier: Operating System :: OS Independent
Requires-Python: >=3.6
